mydatatools/AlgoBaseModelScada.py
mydatatools/MyDataTools.py
mydatatools/PVDataTools.py
mydatatools/__init__.py
mydatatools/read_config.py
mydatatools-1.0.dist-info/METADATA
mydatatools-1.0.dist-info/WHEEL
mydatatools-1.0.dist-info/top_level.txt
mydatatools-1.0.dist-info/RECORD
