Metadata-Version: 2.1
Name: mydatatools
Version: 1.0
Author: zhengquantao80
Author-email: zhengquantao80@gmail.com
Requires-Dist: pandas ==2.2.2
Requires-Dist: SQLAlchemy ==2.0.34
Requires-Dist: PyMySQL ==1.1.1
Requires-Dist: paramiko ==3.4.1
Requires-Dist: loguru ==0.7.2
Requires-Dist: taos-ws-py ==0.3.2
